[{"FullFileName":"Misc\\TheFrogman","Name":"TheFrogman"},{"FullFileName":"Misc\\Oof","Name":"GameOver"},{"FullFileName":"Misc\\DeadAlly","Name":"DeadAlly"},{"FullFileName":"Torment\\Tormentor1.2 (Ablaze)","Name":"Tormentor_Battle"},{"FullFileName":"Torment\\Tormentor1.2","Name":"Tormentor"},{"FullFileName":"Torment\\TormentorIntro","Name":"TormentorIntro"},{"FullFileName":"Torment\\Trickster","Name":"Trickster"},{"FullFileName":"Torment\\Trustworthy","Name":"Trustworthy"},{"FullFileName":"MapThemes\\Dungeon1.2","Name":"Dungeon"},{"FullFileName":"MapThemes\\MagmaFlows2.2","Name":"MagmaFlows"},{"FullFileName":"MapThemes\\ToriTheme","Name":"ToriTheme"},{"FullFileName":"MapThemes\\ToTheDeath2.0","Name":"ToTheDeath"},{"FullFileName":"EventThemes\\ForgottenMemories","Name":"ForgottenMemories"},{"FullFileName":"EventThemes\\Magmaborn","Name":"BeforeBattle"},{"FullFileName":"EventThemes\\Respite","Name":"AfterBattle"},{"FullFileName":"EventThemes\\SafeAndSound","Name":"SafeAndSound"},{"FullFileName":"EventThemes\\ShatteredDream","Name":"ShatteredDream"},{"FullFileName":"EventThemes\\Silence","Name":"Silence"},{"FullFileName":"EventThemes\\Anticipation1.1","Name":"Anticipation"},{"FullFileName":"MapThemes\\Dungeon1.2 (Battle)","Name":"Dungeon_Battle"},{"FullFileName":"MapThemes\\MagmaFlows2.2 (Battle)","Name":"MagmaFlows_Battle"},{"FullFileName":"MapThemes\\ToriTheme (Battle)","Name":"ToriTheme_Battle"},{"FullFileName":"MapThemes\\ToTheDeath2.0 (Battle)","Name":"ToTheDeath_Battle"}]